[
  {
    "location": "slide.leads.stores",
    "battery": 90.00783,
    "reading": "166.82"
  },
  {
    "location": "slips.mass.baking",
    "battery": 0.23880601,
    "reading": "16.996116733095054"
  },
  {
    "location": "paying.crowd.weep",
    "battery": 72.37526,
    "reading": "58.09"
  },
  {
    "location": "hers.banks.goat",
    "battery": 33.337254,
    "reading": "208.64"
  },
  {
    "location": "useful.hike.trades",
    "battery": 80.74631,
    "reading": "121.7"
  },
  {
    "location": "artist.gets.react",
    "battery": 81.47482,
    "reading": "99.76"
  },
  {
    "location": "region.passes.pencil",
    "battery": 21.513199,
    "reading": "61.74"
  },
  {
    "location": "shapes.sheep.nature",
    "battery": 31.284214,
    "reading": "161.93"
  },
  {
    "location": "brings.remedy.latter",
    "battery": 28.681492,
    "reading": "147.8"
  },
  {
    "location": "prime.rent.silk",
    "battery": 18.243694,
    "reading": "209.79"
  },
  {
    "location": "else.urban.museum",
    "battery": 19.52641,
    "reading": "0.0"
  },
  {
    "location": "shut.stands.media",
    "battery": 36.563766,
    "reading": "90.09"
  },
  {
    "location": "spent.spoon.bolt",
    "battery": 33.752525,
    "reading": "164.14"
  },
  {
    "location": "sculpture.shot.melon",
    "battery": 14.724869,
    "reading": "39.92"
  },
  {
    "location": "hidden.handle.softly",
    "battery": 65.421036,
    "reading": "180.1"
  },
  {
    "location": "along.spill.limp",
    "battery": 94.61933,
    "reading": "0.0"
  },
  {
    "location": "stops.else.chats",
    "battery": 78.49596,
    "reading": "242.62"
  },
  {
    "location": "begins.spider.drips",
    "battery": 58.46336,
    "reading": "74.92"
  },
  {
    "location": "turkey.limit.ramp",
    "battery": 27.514816,
    "reading": "122.55"
  },
  {
    "location": "noted.friday.jams",
    "battery": 3.4880698,
    "reading": "212.35908107457638"
  },
  {
    "location": "love.behind.orchestra",
    "battery": 67.00804,
    "reading": "194.59"
  },
  {
    "location": "stone.undulation.poems",
    "battery": 87.26093,
    "reading": "110.56"
  },
  {
    "location": "shady.soft.phones",
    "battery": 13.037491,
    "reading": "132.67"
  },
  {
    "location": "hills.feels.tunes",
    "battery": 88.53935,
    "reading": "200.07"
  },
  {
    "location": "dragon.bottle.crisp",
    "battery": 58.321976,
    "reading": "133.56"
  },
  {
    "location": "teams.mild.played",
    "battery": 21.19096,
    "reading": "192.84"
  },
  {
    "location": "cars.attend.hotels",
    "battery": 42.7879,
    "reading": "45.43"
  },
  {
    "location": "renew.ears.tend",
    "battery": 93.212944,
    "reading": "87.66"
  },
  {
    "location": "simple.rust.audio",
    "battery": 99.82176,
    "reading": "175.79"
  },
  {
    "location": "spoon.invest.every",
    "battery": 28.865088,
    "reading": "37.08"
  },
  {
    "location": "scare.cubs.resort",
    "battery": 81.18235,
    "reading": "39.69"
  },
  {
    "location": "atoms.vanish.foods",
    "battery": 18.789429,
    "reading": "162.12"
  },
  {
    "location": "shows.fries.lamp",
    "battery": 31.530369,
    "reading": "44.17"
  }
]
