[
  {
    "location": "sports.topic.clocks",
    "battery": 69.33192,
    "reading": "148.91"
  },
  {
    "location": "diner.leaves.mutual",
    "battery": 85.138794,
    "reading": "191.26"
  },
  {
    "location": "dragon.bottle.crisp",
    "battery": 49.182777,
    "reading": "134.8"
  },
  {
    "location": "jump.crop.fits",
    "battery": 14.543671,
    "reading": "130.56"
  },
  {
    "location": "shed.desire.muddy",
    "battery": 12.133848,
    "reading": "174.89"
  },
  {
    "location": "turkey.limit.ramp",
    "battery": 91.34741,
    "reading": "187.61"
  },
  {
    "location": "courier.assume.bill",
    "battery": 77.9869,
    "reading": "189.94"
  },
  {
    "location": "brings.remedy.latter",
    "battery": 72.10582,
    "reading": "250.46"
  },
  {
    "location": "scare.cubs.resort",
    "battery": 21.89499,
    "reading": "23.25"
  },
  {
    "location": "toned.deflection.bland",
    "battery": 55.067497,
    "reading": "193.57"
  },
  {
    "location": "love.behind.orchestra",
    "battery": 82.145065,
    "reading": "229.31"
  },
  {
    "location": "bound.ends.matter",
    "battery": 7.7873173,
    "reading": "NaN"
  },
  {
    "location": "burn.spot.across",
    "battery": 25.091034,
    "reading": "56.13"
  },
  {
    "location": "coherent.saints.stuck",
    "battery": 49.961845,
    "reading": "149.05"
  },
  {
    "location": "meal.feed.large",
    "battery": 10.907894,
    "reading": "25.52"
  },
  {
    "location": "skills.less.herb",
    "battery": 39.24747,
    "reading": "163.87"
  },
  {
    "location": "else.urban.museum",
    "battery": 16.500061,
    "reading": "0.0"
  },
  {
    "location": "cars.attend.hotels",
    "battery": 30.329477,
    "reading": "59.57"
  },
  {
    "location": "valve.elaborate.fortunate",
    "battery": 32.199604,
    "reading": "140.78"
  },
  {
    "location": "noted.friday.jams",
    "battery": 50.510334,
    "reading": "20.52"
  },
  {
    "location": "paying.crowd.weep",
    "battery": 11.677444,
    "reading": "46.52"
  },
  {
    "location": "spicy.bunch.shady",
    "battery": 1.4918864,
    "reading": "NaN"
  },
  {
    "location": "prime.rent.silk",
    "battery": 75.93128,
    "reading": "168.46"
  },
  {
    "location": "shows.fries.lamp",
    "battery": 5.509716,
    "reading": "96.73182439129288"
  },
  {
    "location": "cubs.trucks.help",
    "battery": 42.97241,
    "reading": "22.4"
  },
  {
    "location": "useful.hike.trades",
    "battery": 67.966095,
    "reading": "144.67"
  },
  {
    "location": "museum.spicy.horns",
    "battery": 96.85759,
    "reading": "202.58"
  },
  {
    "location": "shut.stands.media",
    "battery": 57.879883,
    "reading": "95.34"
  },
  {
    "location": "panic.squad.danger",
    "battery": 3.2655358,
    "reading": "null"
  },
  {
    "location": "rents.cone.stove",
    "battery": 49.11,
    "reading": "72.05"
  },
  {
    "location": "hills.giant.crate",
    "battery": 74.136314,
    "reading": "33.62"
  },
  {
    "location": "tonic.bliss.cove",
    "battery": 52.979362,
    "reading": "27.9"
  },
  {
    "location": "rider.aura.bulb",
    "battery": 81.49835,
    "reading": "177.7"
  }
]
