[
  {
    "location": "hidden.handle.softly",
    "battery": 89.02829,
    "reading": "132.23"
  },
  {
    "location": "else.urban.museum",
    "battery": 26.729649,
    "reading": "0.0"
  },
  {
    "location": "renew.ears.tend",
    "battery": 40.387154,
    "reading": "113.65"
  },
  {
    "location": "coherent.saints.stuck",
    "battery": 57.425434,
    "reading": "179.45"
  },
  {
    "location": "cliff.asleep.wedge",
    "battery": 78.51032,
    "reading": "42.5"
  },
  {
    "location": "acid.chair.butter",
    "battery": 62.60682,
    "reading": "174.64"
  },
  {
    "location": "second.launch.miles",
    "battery": 5.081004,
    "reading": "167.49377137149153"
  },
  {
    "location": "artist.gets.react",
    "battery": 4.542083,
    "reading": "36.557833211328244"
  },
  {
    "location": "turkey.limit.ramp",
    "battery": 87.11257,
    "reading": "181.42"
  },
  {
    "location": "record.sofa.sock",
    "battery": 19.913881,
    "reading": "192.51"
  },
  {
    "location": "scare.cubs.resort",
    "battery": 80.82534,
    "reading": "25.99"
  },
  {
    "location": "begins.spider.drips",
    "battery": 95.423744,
    "reading": "94.88"
  },
  {
    "location": "gums.clock.modes",
    "battery": 20.30887,
    "reading": "56.13"
  },
  {
    "location": "labels.hotels.alert",
    "battery": 89.41524,
    "reading": "31.55"
  },
  {
    "location": "prime.rent.silk",
    "battery": 82.6177,
    "reading": "237.93"
  },
  {
    "location": "atoms.vanish.foods",
    "battery": 49.47722,
    "reading": "206.71"
  },
  {
    "location": "brings.remedy.latter",
    "battery": 37.305416,
    "reading": "211.49"
  },
  {
    "location": "slide.leads.stores",
    "battery": 8.334362,
    "reading": "NaN"
  },
  {
    "location": "organs.shape.fantastic",
    "battery": 34.079468,
    "reading": "201.97"
  },
  {
    "location": "settle.title.united",
    "battery": 56.616055,
    "reading": "130.44"
  },
  {
    "location": "hills.giant.crate",
    "battery": 96.47063,
    "reading": "31.33"
  },
  {
    "location": "scale.chair.kinds",
    "battery": 39.05591,
    "reading": "164.01"
  },
  {
    "location": "skills.less.herb",
    "battery": 45.527775,
    "reading": "174.34"
  },
  {
    "location": "under.retire.bump",
    "battery": 3.354925,
    "reading": "15.570170765317581"
  },
  {
    "location": "shut.stands.media",
    "battery": 59.51179,
    "reading": "103.45"
  },
  {
    "location": "dent.shins.cycle",
    "battery": 64.04359,
    "reading": "217.37"
  },
  {
    "location": "sports.topic.clocks",
    "battery": 20.717133,
    "reading": "180.65"
  },
  {
    "location": "number.exist.rate",
    "battery": 90.09884,
    "reading": "125.29"
  },
  {
    "location": "hills.feels.tunes",
    "battery": 18.929935,
    "reading": "241.72"
  },
  {
    "location": "relate.chill.vest",
    "battery": 49.50149,
    "reading": "44.5"
  },
  {
    "location": "valve.elaborate.fortunate",
    "battery": 62.835346,
    "reading": "100.36"
  },
  {
    "location": "courier.assume.bill",
    "battery": 74.4774,
    "reading": "188.78"
  },
  {
    "location": "posts.kicked.universally",
    "battery": 62.02275,
    "reading": "252.64"
  }
]
