[
  {
    "location": "hooked.shine.third",
    "battery": 8.483434,
    "reading": "null"
  },
  {
    "location": "pump.wheels.hulk",
    "battery": 12.415302,
    "reading": "32.81"
  },
  {
    "location": "simple.rust.audio",
    "battery": 47.85541,
    "reading": "218.06"
  },
  {
    "location": "paying.crowd.weep",
    "battery": 0.50981045,
    "reading": "NaN"
  },
  {
    "location": "organs.shape.fantastic",
    "battery": 24.471968,
    "reading": "133.02"
  },
  {
    "location": "gums.clock.modes",
    "battery": 65.065094,
    "reading": "68.59"
  },
  {
    "location": "hers.banks.goat",
    "battery": 84.979454,
    "reading": "165.54"
  },
  {
    "location": "spent.spoon.bolt",
    "battery": 65.99193,
    "reading": "205.96"
  },
  {
    "location": "burn.spot.across",
    "battery": 39.492565,
    "reading": "55.53"
  },
  {
    "location": "bound.ends.matter",
    "battery": 62.494213,
    "reading": "72.79"
  },
  {
    "location": "region.passes.pencil",
    "battery": 5.1243544,
    "reading": "NaN"
  },
  {
    "location": "shows.fries.lamp",
    "battery": 88.74992,
    "reading": "45.24"
  },
  {
    "location": "relate.chill.vest",
    "battery": 37.429955,
    "reading": "35.3"
  },
  {
    "location": "hills.giant.crate",
    "battery": 17.844212,
    "reading": "39.6"
  },
  {
    "location": "cubs.trucks.help",
    "battery": 76.529274,
    "reading": "24.42"
  },
  {
    "location": "number.exist.rate",
    "battery": 85.17233,
    "reading": "96.17"
  },
  {
    "location": "manliness.poem.cliff",
    "battery": 60.017956,
    "reading": "153.72"
  },
  {
    "location": "posts.kicked.universally",
    "battery": 68.10816,
    "reading": "219.39"
  },
  {
    "location": "rooms.lamp.teach",
    "battery": 5.4126797,
    "reading": "null"
  },
  {
    "location": "noted.friday.jams",
    "battery": 46.312843,
    "reading": "27.41"
  },
  {
    "location": "courier.assume.bill",
    "battery": 70.634895,
    "reading": "227.7"
  },
  {
    "location": "useful.hike.trades",
    "battery": 54.773376,
    "reading": "153.24"
  },
  {
    "location": "shut.stands.media",
    "battery": 18.314642,
    "reading": "77.81"
  },
  {
    "location": "prime.rent.silk",
    "battery": 14.807439,
    "reading": "200.2"
  },
  {
    "location": "panic.squad.danger",
    "battery": 46.369736,
    "reading": "125.1"
  },
  {
    "location": "acid.chair.butter",
    "battery": 20.183414,
    "reading": "245.47"
  },
  {
    "location": "maple.limit.hotels",
    "battery": 37.525253,
    "reading": "235.11"
  },
  {
    "location": "hills.feels.tunes",
    "battery": 51.65861,
    "reading": "216.24"
  },
  {
    "location": "hidden.handle.softly",
    "battery": 19.104057,
    "reading": "134.84"
  },
  {
    "location": "else.urban.museum",
    "battery": 93.58555,
    "reading": "0.0"
  },
  {
    "location": "second.launch.miles",
    "battery": 42.533077,
    "reading": "35.89"
  },
  {
    "location": "hurt.green.filer",
    "battery": 34.64827,
    "reading": "87.07"
  },
  {
    "location": "toned.deflection.bland",
    "battery": 3.8963616,
    "reading": "105.57723665978806"
  }
]
