[
  {
    "location": "begins.spider.drips",
    "battery": 46.53415,
    "reading": "102.94"
  },
  {
    "location": "rooms.lamp.teach",
    "battery": 12.967938,
    "reading": "152.93"
  },
  {
    "location": "hello.love.keys",
    "battery": 5.4555235,
    "reading": "NaN"
  },
  {
    "location": "skins.engage.best",
    "battery": 58.767162,
    "reading": "153.32"
  },
  {
    "location": "laws.merit.bleak",
    "battery": 25.360321,
    "reading": "243.89"
  },
  {
    "location": "shapes.sheep.nature",
    "battery": 66.25916,
    "reading": "145.62"
  },
  {
    "location": "pump.wheels.hulk",
    "battery": 11.981499,
    "reading": "44.91"
  },
  {
    "location": "scale.chair.kinds",
    "battery": 30.989557,
    "reading": "110.74"
  },
  {
    "location": "stops.else.chats",
    "battery": 11.30715,
    "reading": "142.29"
  },
  {
    "location": "hidden.handle.softly",
    "battery": 71.71215,
    "reading": "171.67"
  },
  {
    "location": "slips.mass.baking",
    "battery": 74.86937,
    "reading": "245.08"
  },
  {
    "location": "dragon.bottle.crisp",
    "battery": 88.54211,
    "reading": "135.07"
  },
  {
    "location": "cliff.asleep.wedge",
    "battery": 70.37355,
    "reading": "41.51"
  },
  {
    "location": "rents.cone.stove",
    "battery": 23.87107,
    "reading": "40.9"
  },
  {
    "location": "slide.leads.stores",
    "battery": 36.144787,
    "reading": "142.15"
  },
  {
    "location": "coherent.saints.stuck",
    "battery": 76.2229,
    "reading": "187.18"
  },
  {
    "location": "spicy.bunch.shady",
    "battery": 56.46198,
    "reading": "32.67"
  },
  {
    "location": "shut.stands.media",
    "battery": 44.733673,
    "reading": "113.98"
  },
  {
    "location": "brings.remedy.latter",
    "battery": 12.265766,
    "reading": "252.33"
  },
  {
    "location": "settle.title.united",
    "battery": 71.570984,
    "reading": "191.1"
  },
  {
    "location": "diner.leaves.mutual",
    "battery": 98.38018,
    "reading": "248.3"
  },
  {
    "location": "renew.slows.basket",
    "battery": 1.1020243,
    "reading": "172.24931710735754"
  },
  {
    "location": "jump.crop.fits",
    "battery": 11.553871,
    "reading": "215.85"
  },
  {
    "location": "simple.rust.audio",
    "battery": 15.822619,
    "reading": "251.0"
  },
  {
    "location": "rush.crown.link",
    "battery": 83.11407,
    "reading": "33.88"
  },
  {
    "location": "museum.spicy.horns",
    "battery": 51.062893,
    "reading": "220.57"
  },
  {
    "location": "bound.ends.matter",
    "battery": 63.951347,
    "reading": "63.01"
  },
  {
    "location": "paying.crowd.weep",
    "battery": 63.110424,
    "reading": "53.18"
  },
  {
    "location": "tonic.bliss.cove",
    "battery": 15.114278,
    "reading": "45.06"
  },
  {
    "location": "organs.shape.fantastic",
    "battery": 50.362682,
    "reading": "205.87"
  },
  {
    "location": "else.urban.museum",
    "battery": 90.15374,
    "reading": "0.0"
  },
  {
    "location": "along.spill.limp",
    "battery": 32.155384,
    "reading": "0.0"
  },
  {
    "location": "panic.squad.danger",
    "battery": 48.367912,
    "reading": "158.86"
  }
]
