[
  {
    "location": "courier.assume.bill",
    "battery": 77.18974,
    "reading": "194.56"
  },
  {
    "location": "system.speak.guard",
    "battery": 29.592323,
    "reading": "24.45"
  },
  {
    "location": "sculpture.shot.melon",
    "battery": 1.9142032,
    "reading": "70.85726039555797"
  },
  {
    "location": "burn.spot.across",
    "battery": 95.739655,
    "reading": "59.7"
  },
  {
    "location": "lime.learns.front",
    "battery": 85.16142,
    "reading": "132.57"
  },
  {
    "location": "sports.topic.clocks",
    "battery": 35.235794,
    "reading": "133.35"
  },
  {
    "location": "brings.remedy.latter",
    "battery": 8.75423,
    "reading": "NaN"
  },
  {
    "location": "cars.attend.hotels",
    "battery": 15.240013,
    "reading": "56.06"
  },
  {
    "location": "museum.spicy.horns",
    "battery": 5.414915,
    "reading": "NaN"
  },
  {
    "location": "strut.river.surely",
    "battery": 75.62639,
    "reading": "132.71"
  },
  {
    "location": "rider.mile.lime",
    "battery": 38.458233,
    "reading": "135.71"
  },
  {
    "location": "along.spill.limp",
    "battery": 40.080814,
    "reading": "0.0"
  },
  {
    "location": "maple.limit.hotels",
    "battery": 33.37658,
    "reading": "154.77"
  },
  {
    "location": "gums.clock.modes",
    "battery": 90.395935,
    "reading": "64.77"
  },
  {
    "location": "boost.radar.stress",
    "battery": 93.87428,
    "reading": "219.78"
  },
  {
    "location": "slips.mass.baking",
    "battery": 7.516819,
    "reading": "null"
  },
  {
    "location": "loaf.cheer.slave",
    "battery": 49.316822,
    "reading": "31.97"
  },
  {
    "location": "atoms.vanish.foods",
    "battery": 64.71597,
    "reading": "171.09"
  },
  {
    "location": "teams.mild.played",
    "battery": 39.581512,
    "reading": "153.91"
  },
  {
    "location": "settle.title.united",
    "battery": 4.232568,
    "reading": "85.50405297139689"
  },
  {
    "location": "relate.chill.vest",
    "battery": 71.80022,
    "reading": "27.67"
  },
  {
    "location": "cubs.trucks.help",
    "battery": 52.665962,
    "reading": "39.4"
  },
  {
    "location": "rated.fired.crowds",
    "battery": 63.527615,
    "reading": "174.76"
  },
  {
    "location": "bend.tubes.chops",
    "battery": 34.64547,
    "reading": "165.21"
  },
  {
    "location": "coherent.saints.stuck",
    "battery": 68.65768,
    "reading": "135.77"
  },
  {
    "location": "panic.squad.danger",
    "battery": 88.20042,
    "reading": "147.52"
  },
  {
    "location": "tonic.bliss.cove",
    "battery": 60.429115,
    "reading": "39.27"
  },
  {
    "location": "labels.hotels.alert",
    "battery": 88.9863,
    "reading": "35.38"
  },
  {
    "location": "hills.giant.crate",
    "battery": 95.53017,
    "reading": "28.02"
  },
  {
    "location": "groups.ideas.script",
    "battery": 79.00957,
    "reading": "42.22"
  },
  {
    "location": "laws.merit.bleak",
    "battery": 25.124252,
    "reading": "218.62"
  },
  {
    "location": "else.urban.museum",
    "battery": 70.74259,
    "reading": "0.0"
  },
  {
    "location": "number.exist.rate",
    "battery": 90.01335,
    "reading": "124.37"
  }
]
